gputop/__init__.py
gputop/cli.py
gputop-3.0.dist-info/METADATA
gputop-3.0.dist-info/WHEEL
gputop-3.0.dist-info/entry_points.txt
gputop-3.0.dist-info/top_level.txt
gputop-3.0.dist-info/RECORD
