Metadata-Version: 2.4
Name: gputop
Version: 3.0
Summary: Real-time GPU monitoring tool
Author-email: Ivan Shivalov <ivansivalov396@gmail.com>
License-Expression: MIT
Project-URL: Homepage, https://github.com/intexcor/gputop
Project-URL: Repository, https://github.com/intexcor/gputop
Project-URL: Issues, https://github.com/intexcor/gputop/issues
Classifier: Development Status :: 3 - Alpha
Classifier: Intended Audience :: Developers
Classifier: Operating System :: OS Independent
Classifier: Programming Language :: Python :: 3
Classifier: Programming Language :: Python :: 3.8
Classifier: Programming Language :: Python :: 3.9
Classifier: Programming Language :: Python :: 3.10
Classifier: Programming Language :: Python :: 3.11
Classifier: Programming Language :: Python :: 3.12
Classifier: Programming Language :: Python :: 3.13
Requires-Python: >=3.8
Requires-Dist: rich
Requires-Dist: psutil
